file_monitor/__init__.py
file_monitor_system-0.1.0.dist-info/METADATA
file_monitor_system-0.1.0.dist-info/WHEEL
file_monitor_system-0.1.0.dist-info/top_level.txt
file_monitor_system-0.1.0.dist-info/RECORD
